noopy/folio/__init__.py
noopy/folio/analyse.py
noopy/folio/optimise.py
noopy/folio/portfolio.py
noopy/folio/screen.py
noopy/folio/select.py
noopy/folio/dataaccessor/__init__.py
noopy/folio/dataaccessor/marketdata.py
noopy/folio/dataaccessor/datastore/rfr_treasury3m.csv
noopy/folio/dataaccessor/datastore/symbols.csv
noopy/folio/dataaccessor/tests/__init__.py
noopy/folio/dataaccessor/tests/test_marketdata.py
noopy/folio/dataaccessor/tests/data/md_aapl.csv
noopy/folio/dataaccessor/tests/data/md_jd.csv
noopy/folio/portfolios/__init__.py
noopy/folio/portfolios/baseportfolio.py
noopy/folio/portfolios/blacklitterman.py
noopy/folio/portfolios/longonly.py
noopy/folio/portfolios/minvariance.py
noopy/folio/portfolios/riskbudgeting.py
noopy/folio/portfolios/tests/__init__.py
noopy/folio/portfolios/tests/test_blacklitterman.py
noopy/folio/portfolios/tests/test_longonly.py
noopy/folio/portfolios/tests/test_minvariance.py
noopy/folio/portfolios/tests/test_riskbudgeting.py
noopy/folio/reporting/__init__.py
noopy/folio/reporting/reports.py
noopy/folio/utils/__init__.py
noopy/folio/utils/math.py
noopy/folio/utils/show.py
noopy/folio/utils/tests/__init__.py
noopy/folio/utils/tests/test_math.py
noopy/folio/utils/tests/test_show.py
noopy_folio-0.0.2.dist-info/licenses/LICENSE
noopy_folio-0.0.2.dist-info/METADATA
noopy_folio-0.0.2.dist-info/WHEEL
noopy_folio-0.0.2.dist-info/top_level.txt
noopy_folio-0.0.2.dist-info/RECORD
