Metadata-Version: 2.4
Name: noopy-folio
Version: 0.0.2
Author-email: Zev Fu <zev.fu@noojing.com>
License: Copyright (c) 2018 The Python Packaging Authority
Keywords: portfolio,quant,finance
Classifier: Development Status :: 3 - Alpha
Classifier: Topic :: Software Development :: Libraries
Classifier: License :: OSI Approved :: CMU License (MIT-CMU)
Requires-Python: >=3.13
License-File: LICENSE
Requires-Dist: matplotlib
Requires-Dist: scikit-learn
Requires-Dist: scipy
Requires-Dist: seaborn
Requires-Dist: tabulate
Requires-Dist: yfinance
Dynamic: license-file
